Workbook

Sheet Leia-me
A1: SupriMax — Dicionário de Dados do Sistema 2 (Cotação Web)
A3: Finalidade | B3: Versão em planilha do dicionário de dados das vinte e duas tabelas do Sistema 2, para consulta rápida, filtro e busca. Complementa a seção 13.7 da “Documentação SupriMax”.
A4: Fonte | B4: Seção 13.7 da “Documentação SupriMax” (dicionário de dados e chaves estrangeiras). Em caso de divergência, prevalece o documento; ao alterar o schema, atualizar documento e planilha juntos.
A5: Banco de dados | B5: Banco único e compartilhado pelos Sistemas 1, 2 e 3 (Supabase/PostgreSQL). Nomes de tabelas e colunas em snake_case, sem acentos.
A7: ABAS
A8: Entidades | B8: Uma linha por tabela: descrição, contagem de colunas e FKs (fórmulas) e uso previsto pelos três sistemas.
A9: Colunas | B9: Dicionário completo: uma linha por coluna, com tipo, restrições em colunas separadas, indicação de nulo e tabela referenciada. Use os filtros do cabeçalho.
A10: Chaves Estrangeiras | B10: As 45 chaves estrangeiras do modelo lógico, com a tabela/coluna referenciada e a obrigatoriedade.
A12: SIGLAS DE RESTRIÇÃO
A13: PK | B13: Chave primária (não nula por definição).
A14: FK | B14: Chave estrangeira (referência na aba Chaves Estrangeiras).
A15: UK | B15: Unicidade (UNIQUE).
A16: NN | B16: Não nulo (NOT NULL).
A17: CK | B17: Restrição de verificação (CHECK); a regra completa está na descrição da coluna e na seção 13.4 da documentação.
A19: OBSERVAÇÕES
A20: Nulos | B20: Colunas sem NN e que não sejam PK aceitam nulo (coluna “Aceita nulo?”, calculada por fórmula).
A21: Uso pelos sistemas | B21: O uso previsto das tabelas pelos Sistemas 1 e 3 foi inferido da documentação de requisitos e ainda deve ser confirmado com os grupos responsáveis.
A22: Escopo | B22: Cobre apenas as tabelas do Sistema 2. Os dicionários dos Sistemas 1 e 3 dependem dos respectivos grupos.
A24: CONFERÊNCIA
A25: Tabelas | B25: =COUNTA(Entidades!$C$5:$C$26) -> 22
A26: Colunas | B26: =COUNTA(Colunas!$C$2:$C$213) -> 212
A27: Chaves estrangeiras | B27: =COUNTA('Chaves Estrangeiras'!$C$5:$C$49) -> 45
A28: Conferência | B28: =IF(AND(B25=22,B26=212,B27=45,Entidades!$E$27=B26,Entidades!$F$27=B27),"OK","DIVERGENTE") -> OK
A29: Referência | B29: Valores esperados, conforme a seção 13.7 da “Documentação SupriMax”: 22 tabelas, 212 colunas e 45 chaves estrangeiras. A conferência também compara os totais da aba Entidades com as abas Colunas e Chaves Estrangeiras.

Sheet Entidades
A1: Entidades do Sistema 2 — visão geral
A2: Contagens calculadas por fórmula a partir da aba Colunas. Uso previsto pelos Sistemas 1 e 3: inferido da documentação de requisitos, a confirmar com os grupos responsáveis.
A4: Nº | B4: Entidade | C4: Tabela | D4: Descrição | E4: Nº de colunas | F4: Nº de FKs | G4: Nº de colunas com CK | H4: Uso previsto — Sistema 1 (mobile) | I4: Uso previsto — Sistema 2 (cotação) | J4: Uso previsto — Sistema 3 (painel) | K4: Origem / observação (checklist)
A5: 1 | B5: Operador/Vendedor | C5: operador | D5: Usuário do sistema em qualquer perfil (vendedor, operador, operador chefe, fiscal, financeiro ou gestor). Login unificado com os Sistemas 1 e 3; o vendedor responde por uma carteira de clientes. | E5: =COUNTIF(Colunas!$A$2:$A$213,C5) -> 11 | F5: =COUNTIFS(Colunas!$A$2:$A$213,C5,Colunas!$F$2:$F$213,"X") -> 0 | G5: =COUNTIFS(Colunas!$A$2:$A$213,C5,Colunas!$I$2:$I$213,"X") -> 3 | H5: Login unificado | I5: Login, perfis e gestão de usuários | J5: Login unificado | K5: Usuário em qualquer perfil (vendedor, operador, operador chefe, fiscal, financeiro ou gestor): login, bloqueio após tentativas inválidas e recuperação de senha.
A6: 2 | B6: Cliente | C6: cliente | D6: Empresa cliente B2B, identificada por CNPJ. Cada cliente pertence a um único vendedor (carteira de clientes). | E6: =COUNTIF(Colunas!$A$2:$A$213,C6) -> 13 | F6: =COUNTIFS(Colunas!$A$2:$A$213,C6,Colunas!$F$2:$F$213,"X") -> 1 | G6: =COUNTIFS(Colunas!$A$2:$A$213,C6,Colunas!$I$2:$I$213,"X") -> 3 | H6: Consulta ao abrir pedido | I6: Cadastro e consulta | J6: Consulta | K6: Cliente B2B por CNPJ; vinculado a um vendedor responsável (carteira de clientes).
A7: 3 | B7: Endereço do Cliente | C7: endereco_cliente | D7: Endereço cadastral ou local de entrega de um cliente (relação 1:N). | E7: =COUNTIF(Colunas!$A$2:$A$213,C7) -> 10 | F7: =COUNTIFS(Colunas!$A$2:$A$213,C7,Colunas!$F$2:$F$213,"X") -> 1 | G7: =COUNTIFS(Colunas!$A$2:$A$213,C7,Colunas!$I$2:$I$213,"X") -> 1 | H7: Consulta ao abrir pedido | I7: Cadastro e consulta | J7: Consulta | K7: Um ou mais endereços/locais de entrega por cliente.
A8: 4 | B8: Produto | C8: produto | D8: Item do catálogo, sem marca ou embalagem definidas. Compartilhado com os Sistemas 1 e 3. | E8: =COUNTIF(Colunas!$A$2:$A$213,C8) -> 7 | F8: =COUNTIFS(Colunas!$A$2:$A$213,C8,Colunas!$F$2:$F$213,"X") -> 0 | G8: =COUNTIFS(Colunas!$A$2:$A$213,C8,Colunas!$I$2:$I$213,"X") -> 0 | H8: Consulta de preços e disponibilidade | I8: Cadastro e consulta | J8: Controle de estoque e indicadores | K8: Código interno, descrição e NCM.
A9: 5 | B9: Variação do Produto | C9: variacao_produto | D9: Combinação de marca e tamanho/embalagem de um produto; é o item de estoque físico independente. O preço não fica aqui: vem das Faixas de Preço (venda avulsa) ou dos Fardos (venda fechada). | E9: =COUNTIF(Colunas!$A$2:$A$213,C9) -> 5 | F9: =COUNTIFS(Colunas!$A$2:$A$213,C9,Colunas!$F$2:$F$213,"X") -> 1 | G9: =COUNTIFS(Colunas!$A$2:$A$213,C9,Colunas!$I$2:$I$213,"X") -> 1 | H9: Consulta de preços e disponibilidade | I9: Cadastro e consulta | J9: Controle de estoque e indicadores | K9: Marca e tamanho/embalagem; item de estoque físico independente.
A10: 6 | B10: Faixa de Preço | C10: faixa_preco | D10: Faixa de preço para venda avulsa de uma variação, por quantidade mínima (ex.: 1 a 3 un. = R$ 25,00; 4+ un. = R$ 19,00). | E10: =COUNTIF(Colunas!$A$2:$A$213,C10) -> 4 | F10: =COUNTIFS(Colunas!$A$2:$A$213,C10,Colunas!$F$2:$F$213,"X") -> 1 | G10: =COUNTIFS(Colunas!$A$2:$A$213,C10,Colunas!$I$2:$I$213,"X") -> 2 | H10: Consulta de preços e disponibilidade | I10: Cadastro e consulta | J10: Controle de estoque e indicadores | K10: Preço por faixa de quantidade, para venda avulsa da variação.
A11: 7 | B11: Fardo | C11: fardo | D11: Opção de venda em pacote fechado de uma variação. Uma variação pode ter mais de um tipo de fardo, cada um com preço próprio. | E11: =COUNTIF(Colunas!$A$2:$A$213,C11) -> 4 | F11: =COUNTIFS(Colunas!$A$2:$A$213,C11,Colunas!$F$2:$F$213,"X") -> 1 | G11: =COUNTIFS(Colunas!$A$2:$A$213,C11,Colunas!$I$2:$I$213,"X") -> 2 | H11: Consulta de preços e disponibilidade | I11: Cadastro e consulta | J11: Controle de estoque e indicadores | K11: Preço fixo por pacote fechado da variação.
A12: 8 | B12: Orçamento | C12: orcamento | D12: Orçamento (cotação de venda) emitido a um cliente por um operador/vendedor, com versões e status (seção 4.6). O orçamento emitido é imutável; os valores aceitos ficam em resposta_orcamento. | E12: =COUNTIF(Colunas!$A$2:$A$213,C12) -> 31 | F12: =COUNTIFS(Colunas!$A$2:$A$213,C12,Colunas!$F$2:$F$213,"X") -> 5 | G12: =COUNTIFS(Colunas!$A$2:$A$213,C12,Colunas!$I$2:$I$213,"X") -> 15 | H12: Lê o orçamento pronto; registra o follow-up | I12: Monta, edita, emite e versiona | J12: Lê para indicadores (RF17) | K12: Cabeçalho do orçamento: número, validade, status, condições, vínculo com o pedido e com a versão original.
A13: 9 | B13: Item de Orçamento | C13: item_orcamento | D13: Linha do orçamento: uma variação, comprada por fardo fechado ou avulso. | E13: =COUNTIF(Colunas!$A$2:$A$213,C13) -> 12 | F13: =COUNTIFS(Colunas!$A$2:$A$213,C13,Colunas!$F$2:$F$213,"X") -> 4 | G13: =COUNTIFS(Colunas!$A$2:$A$213,C13,Colunas!$I$2:$I$213,"X") -> 8 | H13: Lê o orçamento pronto; registra o follow-up | I13: Monta, edita, emite e versiona | J13: Lê para indicadores (RF17) | K13: Linha do orçamento, por fardo fechado ou por faixa avulsa.
A14: 10 | B14: Reserva de Estoque | C14: reserva_estoque | D14: Reserva de saldo físico criada, na emissão do orçamento, para cada item (relação 1:1). Expira junto com a validade do orçamento. | E14: =COUNTIF(Colunas!$A$2:$A$213,C14) -> 5 | F14: =COUNTIFS(Colunas!$A$2:$A$213,C14,Colunas!$F$2:$F$213,"X") -> 1 | G14: =COUNTIFS(Colunas!$A$2:$A$213,C14,Colunas!$I$2:$I$213,"X") -> 2 | H14: Lê o orçamento pronto; registra o follow-up | I14: Monta, edita, emite e versiona | J14: Lê para indicadores (RF17) | K14: Reserva de saldo físico criada, na emissão, para cada item de orçamento (1:1); baixada no aceite.
A15: 11 | B15: Anexo do Orçamento | C15: anexo_orcamento | D15: Arquivo anexado ao orçamento, como descritivo técnico ou material de apoio. | E15: =COUNTIF(Colunas!$A$2:$A$213,C15) -> 7 | F15: =COUNTIFS(Colunas!$A$2:$A$213,C15,Colunas!$F$2:$F$213,"X") -> 1 | G15: =COUNTIFS(Colunas!$A$2:$A$213,C15,Colunas!$I$2:$I$213,"X") -> 1 | H15: Consulta o resultado | I15: Cadastro e consulta | J15: — | K15: Descritivos técnicos e materiais de apoio do orçamento.
A16: 12 | B16: Análise de Crédito | C16: analise_credito | D16: Análise de crédito de um cliente, opcionalmente ligada a um orçamento. | E16: =COUNTIF(Colunas!$A$2:$A$213,C16) -> 7 | F16: =COUNTIFS(Colunas!$A$2:$A$213,C16,Colunas!$F$2:$F$213,"X") -> 3 | G16: =COUNTIFS(Colunas!$A$2:$A$213,C16,Colunas!$I$2:$I$213,"X") -> 2 | H16: Consulta o resultado | I16: Cadastro e consulta | J16: — | K16: Resultado da análise de crédito do cliente.
... A26: 22 | B26: Movimentação de Estoque | C26: movimentacao_estoque | D26: Histórico de toda variação do estoque físico: entradas de mercadoria, baixas no aceite, ajustes e estornos. | E26: =COUNTIF(Colunas!$A$2:$A$213,C26) -> 9 | F26: =COUNTIFS(Colunas!$A$2:$A$213,C26,Colunas!$F$2:$F$213,"X") -> 4 | G26: =COUNTIFS(Colunas!$A$2:$A$213,C26,Colunas!$I$2:$I$213,"X") -> 3 | H26: — | I26: Registra entradas, ajustes e baixas | J26: Controle de estoque | K26: Histórico de entradas, baixas no aceite, ajustes e estornos do estoque físico.
D27: Total | E27: =SUM(E5:E26) -> 212 | F27: =SUM(F5:F26) -> 45 | G27: =SUM(G5:G26) -> 74

Sheet Colunas
A1: Tabela | B1: Nº | C1: Coluna | D1: Tipo | E1: PK | F1: FK | G1: UK | H1: NN | I1: CK | J1: Aceita nulo? | K1: Referencia (FK) | L1: Descrição
A2: operador | B2: 1 | C2: id_operador | D2: INTEGER | E2: X | J2: =IF(OR(E2="X",H2="X"),"Não","Sim") -> Não | L2: Identificador do operador (auto-incremento).
A3: operador | B3: 2 | C3: usuario | D3: VARCHAR(50) | G3: X | H3: X | J3: =IF(OR(E3="X",H3="X"),"Não","Sim") -> Não | L3: Nome de usuário usado no login.
A4: operador | B4: 3 | C4: email | D4: VARCHAR(120) | G4: X | H4: X | J4: =IF(OR(E4="X",H4="X"),"Não","Sim") -> Não | L4: E-mail do usuário; recebe o link de definição e de recuperação de senha.
A5: operador | B5: 4 | C5: senha_hash | D5: VARCHAR(255) | H5: X | J5: =IF(OR(E5="X",H5="X"),"Não","Sim") -> Não | L5: Senha armazenada de forma criptografada (RNF01).
A6: operador | B6: 5 | C6: perfil | D6: VARCHAR(20) | H6: X | I6: X | J6: =IF(OR(E6="X",H6="X"),"Não","Sim") -> Não | L6: VENDEDOR, OPERADOR, OPERADOR_CHEFE, FISCAL, FINANCEIRO ou GESTOR.
A7: operador | B7: 6 | C7: status | D7: VARCHAR(7) | H7: X | I7: X | J7: =IF(OR(E7="X",H7="X"),"Não","Sim") -> Não | L7: ATIVO ou INATIVO. Padrão: ATIVO.
A8: operador | B8: 7 | C8: tentativas_login_invalidas | D8: SMALLINT | H8: X | I8: X | J8: =IF(OR(E8="X",H8="X"),"Não","Sim") -> Não | L8: Contador de tentativas de login inválidas consecutivas; 0 a 3. Padrão: 0.
A9: operador | B9: 8 | C9: bloqueado_ate | D9: TIMESTAMP | J9: =IF(OR(E9="X",H9="X"),"Não","Sim") -> Sim | L9: Momento até o qual o login fica bloqueado; nulo quando não há bloqueio ativo.
A10: operador | B10: 9 | C10: token_recuperacao_senha | D10: VARCHAR(255) | G10: X | J10: =IF(OR(E10="X",H10="X"),"Não","Sim") -> Sim | L10: Token de redefinição de senha enviado por e-mail; nulo fora do fluxo de recuperação.
A11: operador | B11: 10 | C11: validade_token | D11: TIMESTAMP | J11: =IF(OR(E11="X",H11="X"),"Não","Sim") -> Sim | L11: Data e hora limite de uso do token de recuperação; nula quando não há token ativo.
A12: operador | B12: 11 | C12: data_cadastro | D12: TIMESTAMP | H12: X | J12: =IF(OR(E12="X",H12="X"),"Não","Sim") -> Não | L12: Data e hora de criação da conta. Padrão: momento atual.
A13: cliente | B13: 1 | C13: id_cliente | D13: INTEGER | E13: X | J13: =IF(OR(E13="X",H13="X"),"Não","Sim") -> Não | L13: Identificador do cliente (auto-incremento).
A14: cliente | B14: 2 | C14: cnpj | D14: CHAR(14) | G14: X | H14: X | J14: =IF(OR(E14="X",H14="X"),"Não","Sim") -> Não | L14: CNPJ, somente dígitos.
A15: cliente | B15: 3 | C15: razao_social | D15: VARCHAR(150) | H15: X | J15: =IF(OR(E15="X",H15="X"),"Não","Sim") -> Não | L15: Razão social.
A16: cliente | B16: 4 | C16: nome_fantasia | D16: VARCHAR(150) | J16: =IF(OR(E16="X",H16="X"),"Não","Sim") -> Sim | L16: Nome fantasia; opcional, usado na busca por CNPJ, razão social ou nome fantasia (UC14).
A17: cliente | B17: 5 | C17: nome_contato | D17: VARCHAR(100) | H17: X | J17: =IF(OR(E17="X",H17="X"),"Não","Sim") -> Não | L17: Nome do responsável/contato.
A18: cliente | B18: 6 | C18: telefone_contato | D18: VARCHAR(20) | J18: =IF(OR(E18="X",H18="X"),"Não","Sim") -> Sim | L18: Telefone de contato.
A19: cliente | B19: 7 | C19: email_contato | D19: VARCHAR(120) | J19: =IF(OR(E19="X",H19="X"),"Não","Sim") -> Sim | L19: E-mail de contato.
A20: cliente | B20: 8 | C20: tipo_unidade | D20: VARCHAR(6) | H20: X | I20: X | J20: =IF(OR(E20="X",H20="X"),"Não","Sim") -> Não | L20: MATRIZ ou FILIAL.
A21: cliente | B21: 9 | C21: status | D21: VARCHAR(9) | H21: X | I21: X | J21: =IF(OR(E21="X",H21="X"),"Não","Sim") -> Não | L21: ATIVO, INATIVO ou BLOQUEADO. Padrão: ATIVO.
A22: cliente | B22: 10 | C22: id_operador_vendedor | D22: INTEGER | F22: X | H22: X | J22: =IF(OR(E22="X",H22="X"),"Não","Sim") -> Não | K22: operador (id_operador) | L22: Vendedor responsável pela carteira do cliente.
A23: cliente | B23: 11 | C23: aceite_lgpd | D23: BOOLEAN | H23: X | I23: X | J23: =IF(OR(E23="X",H23="X"),"Não","Sim") -> Não | L23: Aceite da cláusula LGPD; só admite TRUE.
A24: cliente | B24: 12 | C24: data_aceite_lgpd | D24: TIMESTAMP | H24: X | J24: =IF(OR(E24="X",H24="X"),"Não","Sim") -> Não | L24: Data e hora do aceite da cláusula LGPD.
A25: cliente | B25: 13 | C25: data_cadastro | D25: TIMESTAMP | H25: X | J25: =IF(OR(E25="X",H25="X"),"Não","Sim") -> Não | L25: Data e hora do cadastro. Padrão: momento atual.
A26: endereco_cliente | B26: 1 | C26: id_endereco | D26: INTEGER | E26: X | J26: =IF(OR(E26="X",H26="X"),"Não","Sim") -> Não | L26: Identificador do endereço (auto-incremento).
A27: endereco_cliente | B27: 2 | C27: id_cliente | D27: INTEGER | F27: X | H27: X | J27: =IF(OR(E27="X",H27="X"),"Não","Sim") -> Não | K27: cliente (id_cliente) | L27: Cliente dono do endereço.
A28: endereco_cliente | B28: 3 | C28: tipo | D28: VARCHAR(10) | H28: X | I28: X | J28: =IF(OR(E28="X",H28="X"),"Não","Sim") -> Não | L28: CADASTRAL ou ENTREGA.
A29: endereco_cliente | B29: 4 | C29: logradouro | D29: VARCHAR(150) | H29: X | J29: =IF(OR(E29="X",H29="X"),"Não","Sim") -> Não | L29: Rua, avenida etc.
A30: endereco_cliente | B30: 5 | C30: numero | D30: VARCHAR(10) | H30: X | J30: =IF(OR(E30="X",H30="X"),"Não","Sim") -> Não | L30: Número (aceita 'S/N').
A31: endereco_cliente | B31: 6 | C31: complemento | D31: VARCHAR(60) | J31: =IF(OR(E31="X",H31="X"),"Não","Sim") -> Sim | L31: Complemento.
A32: endereco_cliente | B32: 7 | C32: bairro | D32: VARCHAR(80) | H32: X | J32: =IF(OR(E32="X",H32="X"),"Não","Sim") -> Não | L32: Bairro.
A33: endereco_cliente | B33: 8 | C33: cidade | D33: VARCHAR(80) | H33: X | J33: =IF(OR(E33="X",H33="X"),"Não","Sim") -> Não | L33: Cidade.
A34: endereco_cliente | B34: 9 | C34: uf | D34: CHAR(2) | H34: X | J34: =IF(OR(E34="X",H34="X"),"Não","Sim") -> Não | L34: Unidade da federação.
A35: endereco_cliente | B35: 10 | C35: cep | D35: CHAR(8) | H35: X | J35: =IF(OR(E35="X",H35="X"),"Não","Sim") -> Não | L35: CEP, somente dígitos.
A36: produto | B36: 1 | C36: id_produto | D36: INTEGER | E36: X | J36: =IF(OR(E36="X",H36="X"),"Não","Sim") -> Não | L36: Identificador do produto (auto-incremento).
A37: produto | B37: 2 | C37: codigo_interno | D37: VARCHAR(30) | G37: X | H37: X | J37: =IF(OR(E37="X",H37="X"),"Não","Sim") -> Não | L37: Código interno do produto.
A38: produto | B38: 3 | C38: descricao | D38: VARCHAR(200) | H38: X | J38: =IF(OR(E38="X",H38="X"),"Não","Sim") -> Não | L38: Descrição do produto.
A39: produto | B39: 4 | C39: ncm | D39: CHAR(8) | J39: =IF(OR(E39="X",H39="X"),"Não","Sim") -> Sim | L39: Classificação fiscal NCM; nulo quando não aplicável.
A40: produto | B40: 5 | C40: ean | D40: VARCHAR(14) | G40: X | J40: =IF(OR(E40="X",H40="X"),"Não","Sim") -> Sim | L40: Código de barras (EAN/GTIN); opcional.
A41: produto | B41: 6 | C41: categoria | D41: VARCHAR(60) | J41: =IF(OR(E41="X",H41="X"),"Não","Sim") -> Sim | L41: Categoria/departamento do produto (UC15); opcional.
A42: produto | B42: 7 | C42: ativo | D42: BOOLEAN | H42: X | J42: =IF(OR(E42="X",H42="X"),"Não","Sim") -> Não | L42: FALSE para produto descontinuado. Padrão: TRUE.
A43: variacao_produto | B43: 1 | C43: id_variacao | D43: INTEGER | E43: X | J43: =IF(OR(E43="X",H43="X"),"Não","Sim") -> Não | L43: Identificador da variação (auto-incremento).
A44: variacao_produto | B44: 2 | C44: id_produto | D44: INTEGER | F44: X | H44: X | J44: =IF(OR(E44="X",H44="X"),"Não","Sim") -> Não | K44: produto (id_produto) | L44: Produto ao qual a variação pertence.
A45: variacao_produto | B45: 3 | C45: marca | D45: VARCHAR(60) | H45: X | J45: =IF(OR(E45="X",H45="X"),"Não","Sim") -> Não | L45: Marca.
A46: variacao_produto | B46: 4 | C46: tamanho_embalagem | D46: VARCHAR(40) | H46: X | J46: =IF(OR(E46="X",H46="X"),"Não","Sim") -> Não | L46: Tamanho ou embalagem (ex.: 1 kg, 5 kg).
A47: variacao_produto | B47: 5 | C47: quantidade_estoque | D47: INTEGER | H47: X | I47: X | J47: =IF(OR(E47="X",H47="X"),"Não","Sim") -> Não | L47: Quantidade em estoque físico à pronta entrega; maior ou igual a zero. Padrão: 0.
A48: faixa_preco | B48: 1 | C48: id_faixa_preco | D48: INTEGER | E48: X | J48: =IF(OR(E48="X",H48="X"),"Não","Sim") -> Não | L48: Identificador da faixa (auto-incremento).
A49: faixa_preco | B49: 2 | C49: id_variacao | D49: INTEGER | F49: X | H49: X | J49: =IF(OR(E49="X",H49="X"),"Não","Sim") -> Não | K49: variacao_produto (id_variacao) | L49: Variação à qual a faixa pertence.
A50: faixa_preco | B50: 3 | C50: quantidade_minima | D50: INTEGER | H50: X | I50: X | J50: =IF(OR(E50="X",H50="X"),"Não","Sim") -> Não | L50: Quantidade mínima para a faixa se aplicar; maior que zero.
A51: faixa_preco | B51: 4 | C51: preco_unitario | D51: DECIMAL(12,2) | H51: X | I51: X | J51: =IF(OR(E51="X",H51="X"),"Não","Sim") -> Não | L51: Preço unitário nessa faixa; maior ou igual a zero.
A52: fardo | B52: 1 | C52: id_fardo | D52: INTEGER | E52: X | J52: =IF(OR(E52="X",H52="X"),"Não","Sim") -> Não | L52: Identificador do fardo (auto-incremento).
A53: fardo | B53: 2 | C53: id_variacao | D53: INTEGER | F53: X | H53: X | J53: =IF(OR(E53="X",H53="X"),"Não","Sim") -> Não | K53: variacao_produto (id_variacao) | L53: Variação à qual o fardo pertence.
A54: fardo | B54: 3 | C54: quantidade_unidades | D54: INTEGER | H54: X | I54: X | J54: =IF(OR(E54="X",H54="X"),"Não","Sim") -> Não | L54: Quantidade de unidades por fardo; maior que zero.
A55: fardo | B55: 4 | C55: preco_fixo | D55: DECIMAL(12,2) | H55: X | I55: X | J55: =IF(OR(E55="X",H55="X"),"Não","Sim") -> Não | L55: Preço fixo do fardo; maior ou igual a zero.
A56: orcamento | B56: 1 | C56: id_orcamento | D56: INTEGER | E56: X | J56: =IF(OR(E56="X",H56="X"),"Não","Sim") -> Não | L56: Identificador interno do orçamento (auto-incremento).
A57: orcamento | B57: 2 | C57: numero_orcamento | D57: BIGINT | G57: X | I57: X | J57: =IF(OR(E57="X",H57="X"),"Não","Sim") -> Sim | L57: Número sequencial único e crescente (mínimo de 5 dígitos na exibição, sem limite superior), sem vínculo com a data. Vem de uma sequence e é atribuído na emissão; nulo em rascunho.
A58: orcamento | B58: 3 | C58: id_cliente | D58: INTEGER | F58: X | H58: X | J58: =IF(OR(E58="X",H58="X"),"Não","Sim") -> Não | K58: cliente (id_cliente) | L58: Cliente do orçamento.
A59: orcamento | B59: 4 | C59: id_operador | D59: INTEGER | F59: X | H59: X | J59: =IF(OR(E59="X",H59="X"),"Não","Sim") -> Não | K59: operador (id_operador) | L59: Operador (Sistema 2) responsável pelo orçamento.
A60: orcamento | B60: 5 | C60: id_endereco_entrega | D60: INTEGER | F60: X | J60: =IF(OR(E60="X",H60="X"),"Não","Sim") -> Sim | K60: endereco_cliente (id_endereco) | L60: Local de entrega escolhido; opcional.
A61: orcamento | B61: 6 | C61: id_pedido | D61: INTEGER | F61: X | J61: =IF(OR(E61="X",H61="X"),"Não","Sim") -> Sim | K61: pedido (id_pedido) | L61: Pedido do Sistema 1 que originou o orçamento; opcional.
A62: orcamento | B62: 7 | C62: id_orcamento_origem | D62: INTEGER | F62: X | J62: =IF(OR(E62="X",H62="X"),"Não","Sim") -> Sim | K62: orcamento (id_orcamento) | L62: Orçamento original, quando este é uma nova versão criada por pedido de alteração; opcional.
A63: orcamento | B63: 8 | C63: data_criacao | D63: TIMESTAMP | H63: X | J63: =IF(OR(E63="X",H63="X"),"Não","Sim") -> Não | L63: Data e hora de criação do rascunho. Padrão: momento atual.
A64: orcamento | B64: 9 | C64: data_ultima_edicao | D64: TIMESTAMP | H64: X | J64: =IF(OR(E64="X",H64="X"),"Não","Sim") -> Não | L64: Data e hora da última edição; base da expiração de 30 dias do rascunho. Padrão: momento atual.
A65: orcamento | B65: 10 | C65: data_encerramento | D65: TIMESTAMP | J65: =IF(OR(E65="X",H65="X"),"Não","Sim") -> Sim | L65: Data e hora em que o orçamento saiu de aberto (aceito, recusado, cancelado, substituído ou expirado); base do apagamento do rascunho expirado 30 dias depois.
A66: orcamento | B66: 11 | C66: data_emissao | D66: DATE | I66: X | J66: =IF(OR(E66="X",H66="X"),"Não","Sim") -> Sim | L66: Data de emissão, definida na emissão; nula em rascunho.
A67: orcamento | B67: 12 | C67: data_validade | D67: DATE | I67: X | J67: =IF(OR(E67="X",H67="X"),"Não","Sim") -> Sim | L67: Data de validade; igual à emissão + 30 dias; nula em rascunho.
A68: orcamento | B68: 13 | C68: status | D68: VARCHAR(20) | H68: X | I68: X | J68: =IF(OR(E68="X",H68="X"),"Não","Sim") -> Não | L68: RASCUNHO, PENDENTE_CREDITO, ABERTO, ALTERACAO_SOLICITADA, ACEITO, RECUSADO, CANCELADO, SUBSTITUIDO ou EXPIRADO (ver seção 4.6). Padrão: RASCUNHO.
A69: orcamento | B69: 14 | C69: motivo_expiracao | D69: VARCHAR(10) | I69: X | J69: =IF(OR(E69="X",H69="X"),"Não","Sim") -> Sim | L69: Preenchido quando status = EXPIRADO: RASCUNHO (30 dias sem edição) ou VALIDADE (30 dias após a emissão).
A70: orcamento | B70: 15 | C70: numero_solicitacao_compra | D70: VARCHAR(30) | J70: =IF(OR(E70="X",H70="X"),"Não","Sim") -> Sim | L70: Número da solicitação de compra do cliente.
A71: orcamento | B71: 16 | C71: contato_solicitacao | D71: VARCHAR(100) | J71: =IF(OR(E71="X",H71="X"),"Não","Sim") -> Sim | L71: Contato específico do cliente vinculado ao orçamento.
A72: orcamento | B72: 17 | C72: prazo_entrega_dias | D72: SMALLINT | I72: X | J72: =IF(OR(E72="X",H72="X"),"Não","Sim") -> Sim | L72: Prazo de entrega em dias, exibido no PDF; maior que zero.
A73: orcamento | B73: 18 | C73: primeira_compra | D73: BOOLEAN | H73: X | J73: =IF(OR(E73="X",H73="X"),"Não","Sim") -> Não | L73: TRUE quando é a primeira compra do cliente (pagamento 100% adiantado); definido pelo backend na abertura do orçamento, a partir do histórico de compras fechadas. Padrão: FALSE.
A74: orcamento | B74: 19 | C74: condicao_pagamento | D74: VARCHAR(16) | I74: X | J74: =IF(OR(E74="X",H74="X"),"Não","Sim") -> Sim | L74: ADIANTADO_100, BOLETO, PARCELADO ou ADIANTADO_50_50 (crédito reprovado); nulo em rascunho.
A75: orcamento | B75: 20 | C75: prazo_dias | D75: SMALLINT | I75: X | J75: =IF(OR(E75="X",H75="X"),"Não","Sim") -> Sim | L75: Prazo do boleto em dias corridos: 10, 15, 20, 28 ou 30; obrigatório quando condicao_pagamento = BOLETO e nulo nos demais casos.
A76: orcamento | B76: 21 | C76: numero_parcelas | D76: SMALLINT | I76: X | J76: =IF(OR(E76="X",H76="X"),"Não","Sim") -> Sim | L76: Número de parcelas, maior que 1; obrigatório quando condicao_pagamento = PARCELADO e nulo nos demais casos.
A77: orcamento | B77: 22 | C77: modalidade_frete | D77: VARCHAR(3) | I77: X | J77: =IF(OR(E77="X",H77="X"),"Não","Sim") -> Sim | L77: CIF (a partir de R$ 1.500,00 ou CIF contratual) ou FOB (abaixo de R$ 1.500,00); nulo em rascunho.
A78: orcamento | B78: 23 | C78: origem_transportadora | D78: VARCHAR(9) | I78: X | J78: =IF(OR(E78="X",H78="X"),"Não","Sim") -> Sim | L78: SUPRIMAX (frete cotado pela SupriMax) ou CLIENTE (transportadora indicada pelo cliente); preenchido só quando modalidade_frete = FOB.
A79: orcamento | B79: 24 | C79: transportadora | D79: VARCHAR(100) | J79: =IF(OR(E79="X",H79="X"),"Não","Sim") -> Sim | L79: Nome da transportadora, quando o frete FOB é cotado ou indicado; opcional.
A80: orcamento | B80: 25 | C80: valor_frete | D80: DECIMAL(12,2) | I80: X | J80: =IF(OR(E80="X",H80="X"),"Não","Sim") -> Sim | L80: Valor do frete destacado no orçamento e na nota fiscal; maior ou igual a zero; nulo quando CIF, quando a transportadora é do cliente ou enquanto o frete não foi cotado.
A81: orcamento | B81: 26 | C81: frete_provisorio | D81: BOOLEAN | H81: X | J81: =IF(OR(E81="X",H81="X"),"Não","Sim") -> Não | L81: TRUE quando o frete FOB ainda não foi cotado com a transportadora; o orçamento sinaliza a provisoriedade (UC18, E3). Padrão: FALSE.
A82: orcamento | B82: 27 | C82: valor_total_itens | D82: DECIMAL(12,2) | I82: X | J82: =IF(OR(E82="X",H82="X"),"Não","Sim") -> Sim | L82: Soma de valor_total_item das linhas (com imposto, sem frete); base de comparação dos limites comerciais. Gravado na emissão; nulo em rascunho.
A83: orcamento | B83: 28 | C83: valor_total_imposto | D83: DECIMAL(12,2) | I83: X | J83: =IF(OR(E83="X",H83="X"),"Não","Sim") -> Sim | L83: Soma de valor_imposto das linhas. Gravado na emissão; nulo em rascunho.
A84: orcamento | B84: 29 | C84: valor_total_proposta | D84: DECIMAL(12,2) | I84: X | J84: =IF(OR(E84="X",H84="X"),"Não","Sim") -> Sim | L84: Valor total da proposta: valor_total_itens + valor_frete (quando destacado). Gravado na emissão; nulo em rascunho.
A85: orcamento | B85: 30 | C85: justificativa | D85: TEXT | J85: =IF(OR(E85="X",H85="X"),"Não","Sim") -> Sim | L85: Motivo do cancelamento/recusa; opcional (aceita nulo ou vazio).
A86: orcamento | B86: 31 | C86: chave_seguranca | D86: VARCHAR(64) | G86: X | J86: =IF(OR(E86="X",H86="X"),"Não","Sim") -> Sim | L86: Hash/código antifraude gerado na emissão; nulo enquanto for rascunho.
A87: item_orcamento | B87: 1 | C87: id_item | D87: INTEGER | E87: X | J87: =IF(OR(E87="X",H87="X"),"Não","Sim") -> Não | L87: Identificador do item (auto-incremento).
A88: item_orcamento | B88: 2 | C88: id_orcamento | D88: INTEGER | F88: X | H88: X | J88: =IF(OR(E88="X",H88="X"),"Não","Sim") -> Não | K88: orcamento (id_orcamento) | L88: Orçamento a que o item pertence.
A89: item_orcamento | B89: 3 | C89: id_variacao | D89: INTEGER | F89: X | H89: X | J89: =IF(OR(E89="X",H89="X"),"Não","Sim") -> Não | K89: variacao_produto (id_variacao) | L89: Variação de produto cotada.
A90: item_orcamento | B90: 4 | C90: granularidade | D90: VARCHAR(6) | H90: X | I90: X | J90: =IF(OR(E90="X",H90="X"),"Não","Sim") -> Não | L90: FARDO ou AVULSO.
A91: item_orcamento | B91: 5 | C91: id_fardo | D91: INTEGER | F91: X | I91: X | J91: =IF(OR(E91="X",H91="X"),"Não","Sim") -> Sim | K91: fardo (id_fardo) | L91: Fardo escolhido; obrigatório quando granularidade = FARDO, nulo quando AVULSO.
A92: item_orcamento | B92: 6 | C92: quantidade_fardos | D92: INTEGER | I92: X | J92: =IF(OR(E92="X",H92="X"),"Não","Sim") -> Sim | L92: Quantidade de fardos, sempre inteira e maior que zero; só quando granularidade = FARDO.
A93: item_orcamento | B93: 7 | C93: id_faixa_preco | D93: INTEGER | F93: X | I93: X | J93: =IF(OR(E93="X",H93="X"),"Não","Sim") -> Sim | K93: faixa_preco (id_faixa_preco) | L93: Faixa de preço aplicada; obrigatória quando granularidade = AVULSO, nula quando FARDO.
A94: item_orcamento | B94: 8 | C94: quantidade_avulsa | D94: INTEGER | I94: X | J94: =IF(OR(E94="X",H94="X"),"Não","Sim") -> Sim | L94: Quantidade avulsa, maior que zero; só quando granularidade = AVULSO.
A95: item_orcamento | B95: 9 | C95: preco_unitario_aplicado | D95: DECIMAL(12,2) | H95: X | I95: X | J95: =IF(OR(E95="X",H95="X"),"Não","Sim") -> Não | L95: Preço unitário efetivamente aplicado (do fardo ou da faixa), congelado na inclusão.
A96: item_orcamento | B96: 10 | C96: valor_imposto | D96: DECIMAL(12,2) | H96: X | I96: X | J96: =IF(OR(E96="X",H96="X"),"Não","Sim") -> Não | L96: Valor do imposto de 18% sobre o valor do item.
A97: item_orcamento | B97: 11 | C97: valor_total_item | D97: DECIMAL(12,2) | H97: X | I97: X | J97: =IF(OR(E97="X",H97="X"),"Não","Sim") -> Não | L97: Valor do item, já com o imposto incluso.
A98: item_orcamento | B98: 12 | C98: aprovacao_herdada | D98: BOOLEAN | H98: X | J98: =IF(OR(E98="X",H98="X"),"Não","Sim") -> Não | L98: TRUE quando o item foi copiado de uma versão anterior já aprovada e não foi alterado; a aprovação exige nova confirmação do cliente. Padrão: FALSE.
A99: reserva_estoque | B99: 1 | C99: id_reserva | D99: INTEGER | E99: X | J99: =IF(OR(E99="X",H99="X"),"Não","Sim") -> Não | L99: Identificador da reserva (auto-incremento).
A100: reserva_estoque | B100: 2 | C100: id_item | D100: INTEGER | F100: X | G100: X | H100: X | J100: =IF(OR(E100="X",H100="X"),"Não","Sim") -> Não | K100: item_orcamento (id_item) | L100: Item de orçamento ao qual a reserva pertence (1:1).
...

Sheet Chaves Estrangeiras
A1: Chaves estrangeiras do modelo lógico
A2: Relações 1:N (lado N = tabela que contém a FK). Exceção: item_orcamento → reserva_estoque é 1:1 (id_item é FK e UK em reserva_estoque).
A4: Nº | B4: Tabela (lado N) | C4: Coluna (FK) | D4: Tabela referenciada (lado 1) | E4: Coluna referenciada | F4: Obrigatória
A5: 1 | B5: cliente | C5: id_operador_vendedor | D5: operador | E5: id_operador | F5: Sim
A6: 2 | B6: endereco_cliente | C6: id_cliente | D6: cliente | E6: id_cliente | F6: Sim
A7: 3 | B7: variacao_produto | C7: id_produto | D7: produto | E7: id_produto | F7: Sim
A8: 4 | B8: faixa_preco | C8: id_variacao | D8: variacao_produto | E8: id_variacao | F8: Sim
A9: 5 | B9: fardo | C9: id_variacao | D9: variacao_produto | E9: id_variacao | F9: Sim
A10: 6 | B10: orcamento | C10: id_cliente | D10: cliente | E10: id_cliente | F10: Sim
A11: 7 | B11: orcamento | C11: id_operador | D11: operador | E11: id_operador | F11: Sim
A12: 8 | B12: orcamento | C12: id_endereco_entrega | D12: endereco_cliente | E12: id_endereco | F12: Não
A13: 9 | B13: item_orcamento | C13: id_orcamento | D13: orcamento | E13: id_orcamento | F13: Sim
A14: 10 | B14: item_orcamento | C14: id_variacao | D14: variacao_produto | E14: id_variacao | F14: Sim
A15: 11 | B15: item_orcamento | C15: id_fardo | D15: fardo | E15: id_fardo | F15: Não
A16: 12 | B16: item_orcamento | C16: id_faixa_preco | D16: faixa_preco | E16: id_faixa_preco | F16: Não
... A49: 45 | B49: analise_credito | C49: id_operador_fiscal | D49: operador | E49: id_operador | F49: Não
